YuanmengXiangmuBijiWangzhuanJuejinShicaoXiangmuDianzishu20200130/README.md
YuanmengXiangmuBijiWangzhuanJuejinShicaoXiangmuDianzishu20200130/__init__.py
YuanmengXiangmuBijiWangzhuanJuejinShicaoXiangmuDianzishu20200130/__main__.py
YuanmengXiangmuBijiWangzhuanJuejinShicaoXiangmuDianzishu20200130/file.pdf
YuanmengXiangmuBijiWangzhuanJuejinShicaoXiangmuDianzishu20200130/index.html
yuanmeng_xiangmu_biji_wangzhuan_juejin_shicao_xiangmu_dianzishu_20200130-2024.3.6.0.dist-info/METADATA
yuanmeng_xiangmu_biji_wangzhuan_juejin_shicao_xiangmu_dianzishu_20200130-2024.3.6.0.dist-info/WHEEL
yuanmeng_xiangmu_biji_wangzhuan_juejin_shicao_xiangmu_dianzishu_20200130-2024.3.6.0.dist-info/entry_points.txt
yuanmeng_xiangmu_biji_wangzhuan_juejin_shicao_xiangmu_dianzishu_20200130-2024.3.6.0.dist-info/top_level.txt
yuanmeng_xiangmu_biji_wangzhuan_juejin_shicao_xiangmu_dianzishu_20200130-2024.3.6.0.dist-info/RECORD
